stefutil/__init__.py
stefutil/built_in.py
stefutil/check_args.py
stefutil/concurrency.py
stefutil/container.py
stefutil/function.py
stefutil/functional.py
stefutil/misc.py
stefutil/ml.py
stefutil/nlp.py
stefutil/os.py
stefutil/os_n_file.py
stefutil/packaging.py
stefutil/plot.py
stefutil/prettier.py
stefutil/primitive.py
stefutil/project.py
stefutil/prettier/__init__.py
stefutil/prettier/prettier.py
stefutil/prettier/prettier_debug.py
stefutil/prettier/prettier_dl.py
stefutil/prettier/prettier_log.py
stefutil/prettier/prettier_progress.py
stefutils-0.48.0.dist-info/LICENSE
stefutils-0.48.0.dist-info/METADATA
stefutils-0.48.0.dist-info/WHEEL
stefutils-0.48.0.dist-info/top_level.txt
stefutils-0.48.0.dist-info/RECORD
